setup.py
httpappengine/__init__.py
httpappengine/aetest.py
httpappengine/decorator.py
httpappengine/helper.py
httpappengine/util.py
httpappengine.egg-info/PKG-INFO
httpappengine.egg-info/SOURCES.txt
httpappengine.egg-info/dependency_links.txt
httpappengine.egg-info/requires.txt
httpappengine.egg-info/top_level.txt
httpappengine/engine/__init__.py
httpappengine/engine/config.py
httpappengine/engine/debug.py
httpappengine/engine/interface.py
httpappengine/engine/parser.py
httpappengine/engine/router.py
httpappengine/engine/scheduler.py
httpappengine/engine/server.py
httpappengine/engine/signaler.py
httpappengine/engine/support.py
httpappengine/engine/util.py
httpappengine/engine/driver/__init__.py
httpappengine/engine/driver/engine_default.py
httpappengine/engine/driver/engine_werkzeug.py
httpappengine/engine/driver/parser_default.py
httpappengine/engine/driver/router_default.py