Metadata-Version: 1.0
Name: httpappengine
Version: 0.3.2
Summary: High performance http engine, Support Django and WebSocket.
Home-page: https://github.com/windprog/appengine
Author: Windpro
Author-email: windprog@gmail.com
License: UNKNOWN
Platform: UNKNOWN
